{"assets":{"383E4D4030138E242A171E1F7F7AD7A6":{"type":"texture","index":1,"assetRequest":{"type":"slide","state":"contents","slide":"none"},"url":{"native":"assets\/281B908F-E416-43C6-80C6-8878F72FE325.pdf"},"width":1920,"height":1080},"ACBE09D040ED7BE1583652631C623DA5":{"type":"texture","index":0,"assetRequest":{"type":"slide","state":"contents","slide":"none"},"url":{"native":"assets\/281B908F-E416-43C6-80C6-8878F72FE325.pdf"},"width":1920,"height":1080}},"events":[{"effects":[{"beginTime":0,"baseLayer":{"animations":[],"initialState":{"affineTransform":[1,0,0,1,0,0],"masksToBounds":false,"rotation":0,"scale":1,"position":{"pointX":960,"pointY":540},"width":1920,"sublayerTransform":[1,0,0,0,0,1,0,0,0,0,1,0,0,0,0,1],"contentsRect":{"y":0,"x":0,"width":1,"height":1},"opacity":1,"edgeAntialiasingMask":251658240,"height":1080,"hidden":false,"anchorPoint":{"pointX":0.5,"pointY":0.5}},"objectID":"0","layers":[{"animations":[],"initialState":{"affineTransform":[1,0,0,1,0,0],"masksToBounds":false,"rotation":0,"scale":1,"position":{"pointX":960,"pointY":540},"width":1920,"sublayerTransform":[1,0,0,0,0,1,0,0,0,0,1,-0.00035007912466775983,0,0,0,1],"contentsRect":{"y":0,"x":0,"width":1,"height":1},"opacity":1,"edgeAntialiasingMask":251658240,"height":1080,"hidden":false,"anchorPoint":{"pointX":0.5,"pointY":0.5}},"layers":[{"animations":[],"layers":[],"texturedRectangle":{"isBackgroundTexture":false,"singleTextureOpacity":1,"textureType":0,"textBaseline":0,"textXHeight":0,"isVerticalText":false},"initialState":{"affineTransform":[1,0,0,1,0,0],"masksToBounds":false,"rotation":0,"scale":1,"position":{"pointX":960,"pointY":540},"width":1920,"sublayerTransform":[1,0,0,0,0,1,0,0,0,0,1,0,0,0,0,1],"contentsRect":{"y":0,"x":0,"width":1,"height":1},"opacity":1,"edgeAntialiasingMask":0,"height":1080,"hidden":false,"anchorPoint":{"pointX":0.5,"pointY":0.5}},"texture":"383E4D4030138E242A171E1F7F7AD7A6"},{"animations":[{"additive":false,"timeOffset":0,"beginTime":0,"from":{"scalar":false},"repeatCount":0,"fillMode":"both","duration":0.01,"autoreverses":false,"property":"hidden","to":{"scalar":true},"removedOnCompletion":false}],"layers":[],"texturedRectangle":{"isBackgroundTexture":false,"singleTextureOpacity":1,"textureType":0,"textBaseline":0,"textXHeight":0,"isVerticalText":false},"initialState":{"affineTransform":[1,0,0,1,0,0],"masksToBounds":false,"rotation":0,"scale":1,"position":{"pointX":960,"pointY":540},"width":1920,"sublayerTransform":[1,0,0,0,0,1,0,0,0,0,1,0,0,0,0,1],"contentsRect":{"y":0,"x":0,"width":1,"height":1},"opacity":1,"edgeAntialiasingMask":0,"height":1080,"hidden":false,"anchorPoint":{"pointX":0.5,"pointY":0.5}},"texture":"ACBE09D040ED7BE1583652631C623DA5"}]}]},"effects":[],"duration":0.01,"type":"transition","attributes":{"direction":0},"name":"none","objectID":"0"}],"automaticPlay":false,"hyperlinks":[],"accessibility":[{"text":"Homework - Part 1","targetRectangle":{"y":100,"x":100,"width":668.19900053577112,"height":140.79994285106659}},{"text":"Make a new folder called “wd3_week1_homework”, and add a copy of the circus starter to it. Create a git repository with that project and do the following:","targetRectangle":{"y":287,"x":154.00000476837158,"width":1642.6469999999999,"height":63.000000417232513}},{"text":"Commit the default circus starter project with the message “Initial Commit”","targetRectangle":{"y":343.00000083446503,"x":208.00000476837158,"width":985.47800000000007,"height":59}},{"text":"Delete the contents of README.md and replace it with “<your name> - WD3 - Git Homework”","targetRectangle":{"y":395.00000125169754,"x":208.00000476837158,"width":1218.6670000000001,"height":59}},{"text":"Use markdown syntax to make your name bold in the readme and the “WD3 - Git Homework” part cursive","targetRectangle":{"y":447.00000166893005,"x":208.00000476837158,"width":1383.6480000000004,"height":59}},{"text":"Delete the body of the HTML file and replace it with basic markup that includes your name, your quarter, and a list of three things that this pandemic has taught you","targetRectangle":{"y":499.00000208616257,"x":208.00000476837158,"width":1607.789,"height":87.000000417232513}},{"text":"Commit this to the master branch with the message \\\"Second commit\\\"","targetRectangle":{"y":579.00000292062759,"x":208.00000476837158,"width":911.73099999999999,"height":59}},{"text":"Next, demonstrate the use of branches:","targetRectangle":{"y":631.00000333786011,"x":154.00000476837158,"width":515.85199999999998,"height":59}},{"text":"Make a new branch called “styling\\\"","targetRectangle":{"y":683.00000375509262,"x":208.00000476837158,"width":459.82399999999984,"height":59}},{"text":"Add some color and font settings to make your HTML page look nicer. Like you would want an “About Me” page on your portfolio to look","targetRectangle":{"y":735.00000417232513,"x":208.00000476837158,"width":1575.8889999999999,"height":87.000000417232513}},{"text":"Commit your changes to the “styling” branch as you make them. Make sure your commit messages describe what you've done. I want to see at least two commits","targetRectangle":{"y":815.00000500679016,"x":208.00000476837158,"width":1589.3160000000003,"height":87.000000417232513}},{"text":"Merge those changes back into the main branch","targetRectangle":{"y":895.00000584125519,"x":208.00000476837158,"width":631.8520000000002,"height":59}}],"baseLayer":{"animations":[],"initialState":{"affineTransform":[1,0,0,1,0,0],"masksToBounds":false,"rotation":0,"scale":1,"position":{"pointX":960,"pointY":540},"width":1920,"sublayerTransform":[1,0,0,0,0,1,0,0,0,0,1,0,0,0,0,1],"contentsRect":{"y":0,"x":0,"width":1,"height":1},"opacity":1,"edgeAntialiasingMask":251658240,"height":1080,"hidden":false,"anchorPoint":{"pointX":0.5,"pointY":0.5}},"objectID":"0","layers":[{"animations":[],"initialState":{"affineTransform":[1,0,0,1,0,0],"masksToBounds":false,"rotation":0,"scale":1,"position":{"pointX":960,"pointY":540},"width":1920,"sublayerTransform":[1,0,0,0,0,1,0,0,0,0,1,-0.00035007912466775983,0,0,0,1],"contentsRect":{"y":0,"x":0,"width":1,"height":1},"opacity":1,"edgeAntialiasingMask":251658240,"height":1080,"hidden":false,"anchorPoint":{"pointX":0.5,"pointY":0.5}},"layers":[{"animations":[],"layers":[],"texturedRectangle":{"isBackgroundTexture":false,"singleTextureOpacity":1,"textureType":0,"textBaseline":0,"textXHeight":0,"isVerticalText":false},"initialState":{"affineTransform":[1,0,0,1,0,0],"masksToBounds":false,"rotation":0,"scale":1,"position":{"pointX":960,"pointY":540},"width":1920,"sublayerTransform":[1,0,0,0,0,1,0,0,0,0,1,0,0,0,0,1],"contentsRect":{"y":0,"x":0,"width":1,"height":1},"opacity":1,"edgeAntialiasingMask":0,"height":1080,"hidden":false,"anchorPoint":{"pointX":0.5,"pointY":0.5}},"texture":"ACBE09D040ED7BE1583652631C623DA5"}]}]}}]}